json2csv.py
zencore_json2csv-0.2.1.dist-info/LICENSE
zencore_json2csv-0.2.1.dist-info/METADATA
zencore_json2csv-0.2.1.dist-info/WHEEL
zencore_json2csv-0.2.1.dist-info/entry_points.txt
zencore_json2csv-0.2.1.dist-info/top_level.txt
zencore_json2csv-0.2.1.dist-info/RECORD
